amazoncaptcha/__init__.py
amazoncaptcha/__version__.py
amazoncaptcha/devtools.py
amazoncaptcha/exceptions.py
amazoncaptcha/solver.py
amazoncaptcha/utils.py
amazoncaptcha/training_data/A.json
amazoncaptcha/training_data/B.json
amazoncaptcha/training_data/C.json
amazoncaptcha/training_data/E.json
amazoncaptcha/training_data/F.json
amazoncaptcha/training_data/G.json
amazoncaptcha/training_data/H.json
amazoncaptcha/training_data/J.json
amazoncaptcha/training_data/K.json
amazoncaptcha/training_data/L.json
amazoncaptcha/training_data/M.json
amazoncaptcha/training_data/N.json
amazoncaptcha/training_data/P.json
amazoncaptcha/training_data/R.json
amazoncaptcha/training_data/T.json
amazoncaptcha/training_data/U.json
amazoncaptcha/training_data/X.json
amazoncaptcha/training_data/Y.json
amazoncaptcha-0.5.11.dist-info/LICENSE
amazoncaptcha-0.5.11.dist-info/METADATA
amazoncaptcha-0.5.11.dist-info/WHEEL
amazoncaptcha-0.5.11.dist-info/top_level.txt
amazoncaptcha-0.5.11.dist-info/RECORD
