Metadata-Version: 2.1
Name: amazoncaptcha
Version: 0.5.11
Summary: "Pure Python, lightweight, Pillow-based solver for the Amazon text captcha."
Home-page: https://github.com/a-maliarov/amazoncaptcha
Author: Anatolii Maliarov
Author-email: tly.mov@gmail.com
Project-URL: Documentation, https://amazoncaptcha.readthedocs.io/en/latest/
Project-URL: Source, https://github.com/a-maliarov/amazoncaptcha
Classifier: Programming Language :: Python :: 3.6
Classifier: Programming Language :: Python :: 3.7
Classifier: Programming Language :: Python :: 3.8
Classifier: Programming Language :: Python :: 3.9
Classifier: License :: OSI Approved :: MIT License
Classifier: Operating System :: OS Independent
Classifier: Development Status :: 5 - Production/Stable
Classifier: Natural Language :: English
Classifier: Intended Audience :: Developers
Classifier: Intended Audience :: Education
Classifier: Intended Audience :: Information Technology
License-File: LICENSE
